pydantic_ui/__init__.py
pydantic_ui/app.py
pydantic_ui/config.py
pydantic_ui/controller.py
pydantic_ui/events.py
pydantic_ui/handlers.py
pydantic_ui/models.py
pydantic_ui/schema.py
pydantic_ui/sessions.py
pydantic_ui/utils.py
pydantic_ui/static/index.html
pydantic_ui/static/logo.png
pydantic_ui/static/assets/index-BCHZmOPM.js
pydantic_ui/static/assets/index-BFHm9gCR.css
pydantic_ui-0.1.6.dist-info/METADATA
pydantic_ui-0.1.6.dist-info/WHEEL
pydantic_ui-0.1.6.dist-info/RECORD
