Metadata-Version: 2.4
Name: pydantic-ui
Version: 0.1.6
Summary: Dynamic UI for editing deeply nested Pydantic models
Project-URL: Homepage, https://github.com/idling-mind/pydantic-ui
Project-URL: Documentation, https://github.com/idling-mind/pydantic-ui#readme
Project-URL: Repository, https://github.com/idling-mind/pydantic-ui
Project-URL: Issues, https://github.com/idling-mind/pydantic-ui/issues
Author-email: Najeem Muhammed <najeem@gmail.com>
License-Expression: MIT
Keywords: editor,fastapi,form,pydantic,react,ui
Classifier: Development Status :: 3 - Alpha
Classifier: Framework :: FastAPI
Classifier: Framework :: Pydantic :: 2
Classifier: Intended Audience :: Developers
Classifier: License :: OSI Approved :: MIT License
Classifier: Operating System :: OS Independent
Classifier: Programming Language :: Python :: 3
Classifier: Programming Language :: Python :: 3.10
Classifier: Programming Language :: Python :: 3.11
Classifier: Programming Language :: Python :: 3.12
Classifier: Topic :: Software Development :: Libraries :: Python Modules
Classifier: Typing :: Typed
Requires-Python: >=3.10
Requires-Dist: fastapi>=0.100.0
Requires-Dist: pydantic>=2.0.0
Requires-Dist: uvicorn>=0.23.0
Provides-Extra: dev
Requires-Dist: coverage>=7.4.0; extra == 'dev'
Requires-Dist: faker>=22.0.0; extra == 'dev'
Requires-Dist: httpx>=0.27.0; extra == 'dev'
Requires-Dist: mypy>=1.8.0; extra == 'dev'
Requires-Dist: pytest-asyncio>=0.23.0; extra == 'dev'
Requires-Dist: pytest-cov>=4.1.0; extra == 'dev'
Requires-Dist: pytest-mock>=3.12.0; extra == 'dev'
Requires-Dist: pytest>=8.0.0; extra == 'dev'
Requires-Dist: ruff>=0.1.0; extra == 'dev'
